{
    "date_compare_now": ["Paid Until"], 
    "hidden_columns": ["Rent Until Value", "leaseid", "Paid Until Value", "tenantid"], 
    "hyperlink": 
    {
        "Apartment Name":
        {
            "controller": "apartment", 
            "action": "edit", 
            "object_id": "ID"
        }, 
        "Tenant Name":
        {
            "controller": "tenant", 
            "action": "edit", 
            "object_id": "tenantid"
        }, 
        "Rent Until":
        {
            "controller": "leaseagrm", 
            "action": "edit", 
            "object_id": "leaseid"
        }
    }, 
    "hyperlink_list": ["Ocupant Name"], 
    "page_title": "Overview", 
    "search": ["Apartment Name", "Tenant Name", "Rent Until", "Paid Until"], 
    "sort": 
    {
        "Rent Until": "Rent Until Value", 
        "Paid Until": "Paid Until Value", 
        "Apartment Name": "Apartment Name"
    }
}